codat_platform/__init__.py
codat_platform/_hooks/__init__.py
codat_platform/_hooks/registration.py
codat_platform/_hooks/sdkhooks.py
codat_platform/_hooks/types.py
codat_platform/_version.py
codat_platform/basesdk.py
codat_platform/companies.py
codat_platform/connection_management.py
codat_platform/connections.py
codat_platform/cors.py
codat_platform/custom_data_type.py
codat_platform/httpclient.py
codat_platform/integrations.py
codat_platform/models/errors/__init__.py
codat_platform/models/errors/errormessage.py
codat_platform/models/errors/sdkerror.py
codat_platform/models/operations/__init__.py
codat_platform/models/operations/add_product.py
codat_platform/models/operations/configure_custom_data_type.py
codat_platform/models/operations/configure_supplemental_data.py
codat_platform/models/operations/create_connection.py
codat_platform/models/operations/delete_api_key.py
codat_platform/models/operations/delete_company.py
codat_platform/models/operations/delete_connection.py
codat_platform/models/operations/delete_webhook_consumer.py
codat_platform/models/operations/get_company.py
codat_platform/models/operations/get_company_access_token.py
codat_platform/models/operations/get_company_data_status.py
codat_platform/models/operations/get_company_push_history.py
codat_platform/models/operations/get_connection.py
codat_platform/models/operations/get_connection_management_access_token.py
codat_platform/models/operations/get_create_update_model_options_by_data_type.py
codat_platform/models/operations/get_custom_data_type_configuration.py
codat_platform/models/operations/get_integration.py
codat_platform/models/operations/get_integrations_branding.py
codat_platform/models/operations/get_pull_operation.py
codat_platform/models/operations/get_push_operation.py
codat_platform/models/operations/get_supplemental_data_configuration.py
codat_platform/models/operations/list_companies.py
codat_platform/models/operations/list_connections.py
codat_platform-4.2.0.dist-info/METADATA
codat_platform-4.2.0.dist-info/WHEEL
codat_platform-4.2.0.dist-info/RECORD
